sshow.py
sshow-0.1.1.dist-info/METADATA
sshow-0.1.1.dist-info/WHEEL
sshow-0.1.1.dist-info/entry_points.txt
sshow-0.1.1.dist-info/top_level.txt
sshow-0.1.1.dist-info/RECORD
