Metadata-Version: 2.4
Name: sshow
Version: 0.1.1
Summary: Prettify and group your ~/.ssh/config.
Author-email: Chuan Peng <erichuanp@gmail.com>
License: MIT
Requires-Python: >=3.8
